setup.py
coinkit/__init__.py
coinkit/address.py
coinkit/b58check.py
coinkit/constants.py
coinkit/errors.py
coinkit/formatcheck.py
coinkit/hash.py
coinkit/keypair.py
coinkit/merkle.py
coinkit/privatekey.py
coinkit/publickey.py
coinkit/wallet.py
coinkit.egg-info/PKG-INFO
coinkit.egg-info/SOURCES.txt
coinkit.egg-info/dependency_links.txt
coinkit.egg-info/not-zip-safe
coinkit.egg-info/requires.txt
coinkit.egg-info/top_level.txt
coinkit/passphrases/__init__.py
coinkit/passphrases/english_words.py
coinkit/passphrases/legacy.py
coinkit/passphrases/passphrase.py
coinkit/services/__init__.py
coinkit/services/bitcoind.py
coinkit/services/blockchain_client.py
coinkit/services/blockchain_info.py
coinkit/services/chain_com.py
coinkit/transactions/__init__.py
coinkit/transactions/network.py
coinkit/transactions/opcodes.py
coinkit/transactions/outputs.py
coinkit/transactions/scripts.py
coinkit/transactions/serialize.py
coinkit/transactions/utils.py