Metadata-Version: 1.1
Name: coinkit
Version: 0.7.8
Summary: Tools for Bitcoin & other cryptocurrencies (incl. Namecoin, Litecoin, Dogecoin, etc.).
Home-page: https://github.com/onenameio/coinkit
Author: Onename (Halfmoon Labs)
Author-email: hello@halfmoon.io
License: MIT
Keywords: bitcoin btc litecoin namecoin dogecoin cryptocurrency
Platform: UNKNOWN
Classifier: Intended Audience :: Developers
Classifier: License :: OSI Approved :: MIT License
Classifier: Operating System :: OS Independent
Classifier: Programming Language :: Python
Classifier: Topic :: Internet
Classifier: Topic :: Security :: Cryptography
Classifier: Topic :: Software Development :: Libraries :: Python Modules
